README.rst
setup.cfg
setup.py
docio/__init__.py
docio.egg-info/PKG-INFO
docio.egg-info/SOURCES.txt
docio.egg-info/dependency_links.txt
docio.egg-info/not-zip-safe
docio.egg-info/pbr.json
docio.egg-info/requires.txt
docio.egg-info/top_level.txt